{
  "updated": "2026-01-31T06:01:41.847403-05:00",
  "total_trades": 255,
  "wins": 234,
  "losses": 21,
  "win_rate": 91.76,
  "total_pnl": 31027.5,
  "by_product": {
    "STRIKE": {
      "trades": 255,
      "win_rate": 91.76,
      "pnl": 31027.5
    },
    "PATROL": {
      "trades": 0,
      "win_rate": 0,
      "pnl": 0
    }
  },
  "by_engine": {
    "PRIME": {
      "trades": 0,
      "win_rate": 0,
      "pnl": 0
    },
    "SPRINT": {
      "trades": 0,
      "win_rate": 0,
      "pnl": 0
    },
    "AKRON": {
      "trades": 0,
      "win_rate": 0,
      "pnl": 0
    },
    "AGEMA": {
      "trades": 0,
      "win_rate": 0,
      "pnl": 0
    }
  },
  "shield": {
    "accuracy": 0.0,
    "breach_rate": 0.0,
    "breach_depth": 0,
    "recovery_rate": 0,
    "total_with_shield": 254
  }
}